TritonHub/__init__.py
TritonHub/Activations/__init__.py
TritonHub/Activations/gelu.py
TritonHub/Activations/leaky_relu.py
TritonHub/Activations/mish.py
TritonHub/Activations/relu.py
TritonHub/Activations/sigmoid.py
TritonHub/Activations/silu.py
TritonHub/Activations/softmax.py
TritonHub/Activations/softmin.py
TritonHub/Activations/softplus.py
TritonHub/Activations/tanh.py
TritonHub/Layers/__init__.py
TritonHub/Layers/linear.py
TritonHub/Normalization/__init__.py
TritonHub/Normalization/layernorm.py
TritonHub/Normalization/rmsnorm.py
TritonHub-1.0.2.dist-info/LICENSE
TritonHub-1.0.2.dist-info/METADATA
TritonHub-1.0.2.dist-info/WHEEL
TritonHub-1.0.2.dist-info/top_level.txt
TritonHub-1.0.2.dist-info/RECORD
