Metadata-Version: 2.1
Name: TritonHub
Version: 1.0.2
Summary: A collection of Triton-based neural network modules
Home-page: https://github.com/AliYoussef97/Triton-Factory
Author: Ali Youssef
Requires-Python: >=3.7
License-File: LICENSE
Requires-Dist: torch
Requires-Dist: triton
